cogs/__init__.py
coglist-1.0.1.dist-info/LICENSE
coglist-1.0.1.dist-info/METADATA
coglist-1.0.1.dist-info/WHEEL
coglist-1.0.1.dist-info/top_level.txt
coglist-1.0.1.dist-info/RECORD
