Metadata-Version: 2.1
Name: coglist
Version: 1.0.1
Summary: A collection of cogs to create Discord bots with.
Home-page: https://github.com/coglist/cogs
Author: vcokltfre, elfq, tag-epic
License: MIT
Platform: UNKNOWN
Requires-Python: >=3.6
Requires-Dist: templatebot
